lean_interact/__init__.py
lean_interact/config.py
lean_interact/interface.py
lean_interact/pool.py
lean_interact/project.py
lean_interact/server.py
lean_interact/sessioncache.py
lean_interact/utils.py
lean_interact/py.typed
lean_interact-0.11.0.dist-info/METADATA
lean_interact-0.11.0.dist-info/WHEEL
lean_interact-0.11.0.dist-info/entry_points.txt
lean_interact-0.11.0.dist-info/licenses/LICENSE
lean_interact-0.11.0.dist-info/RECORD
