Metadata-Version: 2.4
Name: lean-interact
Version: 0.11.0
Summary: LeanInteract is a Python package that allows you to interact with the Lean theorem prover.
Author-email: Auguste Poiroux <auguste.poiroux@epfl.ch>
License: MIT License
License-File: LICENSE
Keywords: Lean,REPL,autoformalization,theorem proving
Requires-Python: >=3.10
Requires-Dist: filelock>=3.18.0
Requires-Dist: gitpython>=3.1.44
Requires-Dist: packaging>=24.2
Requires-Dist: psutil>=6.1.0
Requires-Dist: pydantic>=2.11.1
Requires-Dist: requests>=2.32.3
Requires-Dist: rich>=13.9.4
Requires-Dist: tqdm>=4.67.1
